PJYSDK/PJYSDK.py
PJYSDK/__init__.py
pjysdk-1.0.8.dist-info/licenses/LICENSE
pjysdk-1.0.8.dist-info/METADATA
pjysdk-1.0.8.dist-info/WHEEL
pjysdk-1.0.8.dist-info/top_level.txt
pjysdk-1.0.8.dist-info/RECORD
