Metadata-Version: 2.4
Name: PJYSDK
Version: 1.0.8
Summary: 泡椒云网络验证 Python SDK
Home-page: https://www.paojiaoyun.com
Author: huaishan
Author-email: admin@paojiaoyun.com
Project-URL: Docs, https://docs.paojiaoyun.com/py_sdk.html
Classifier: Programming Language :: Python :: 3
Classifier: License :: OSI Approved :: MIT License
Classifier: Operating System :: OS Independent
Requires-Python: >=3.6
License-File: LICENSE
Requires-Dist: requests>=2.27
Dynamic: author
Dynamic: author-email
Dynamic: classifier
Dynamic: description
Dynamic: description-content-type
Dynamic: home-page
Dynamic: license-file
Dynamic: project-url
Dynamic: requires-dist
Dynamic: requires-python
Dynamic: summary
